tawpy/__init__.py
tawpy/api.py
tawpy/enums.py
tawpy/errors.py
tawpy/http_tenor.py
Tawpy-0.1.1.dist-info/METADATA
Tawpy-0.1.1.dist-info/WHEEL
Tawpy-0.1.1.dist-info/top_level.txt
Tawpy-0.1.1.dist-info/RECORD
