Metadata-Version: 2.1
Name: Tawpy
Version: 0.1.1
Summary: For requesting gifs from the tenor website
Home-page: https://github.com/devKeef/Tawpy
Author: dvKeef
Author-email: senkokunt@gmail.com
License: UNKNOWN
Platform: UNKNOWN
Classifier: Programming Language :: Python :: 3
Classifier: License :: OSI Approved :: MIT License
Classifier: Operating System :: OS Independent
Requires-Python: >=3
